phis_introducing_med/__init__.py
phis_introducing_med/delete_existing.py
phis_introducing_med/extract_med_data.py
phis_introducing_med/handle_popup.py
phis_introducing_med/introducing_history_meds.py
phis_introducing_med/introducing_medication.py
phis_introducing_med/is_drug_name_similar.py
phis_introducing_med/save_med_records.py
phis_introducing_med-2025.7.31.0.dist-info/METADATA
phis_introducing_med-2025.7.31.0.dist-info/WHEEL
phis_introducing_med-2025.7.31.0.dist-info/licenses/LICENSE
phis_introducing_med-2025.7.31.0.dist-info/RECORD
