Metadata-Version: 2.4
Name: phis-introducing-med
Version: 2025.7.31.0
Summary: 宇信慢病随访新建-引入用药
License-File: LICENSE
Requires-Python: >=3.12
Requires-Dist: soda-kapybara>=2025.7.22.1
Requires-Dist: yxmb-compatlib>=2025.7.30.6
